TensorflowZhinengYidongXiangmuChuyiFix1/README.md
TensorflowZhinengYidongXiangmuChuyiFix1/__init__.py
TensorflowZhinengYidongXiangmuChuyiFix1/__main__.py
TensorflowZhinengYidongXiangmuChuyiFix1/file.epub
TensorflowZhinengYidongXiangmuChuyiFix1/index.html
TensorflowZhinengYidongXiangmuChuyiFix1/css/__init__.py
TensorflowZhinengYidongXiangmuChuyiFix1/css/annotations.css
TensorflowZhinengYidongXiangmuChuyiFix1/css/main.css
TensorflowZhinengYidongXiangmuChuyiFix1/css/normalize.css
TensorflowZhinengYidongXiangmuChuyiFix1/css/popup.css
TensorflowZhinengYidongXiangmuChuyiFix1/font/__init__.py
TensorflowZhinengYidongXiangmuChuyiFix1/font/fontello.eot
TensorflowZhinengYidongXiangmuChuyiFix1/font/fontello.svg
TensorflowZhinengYidongXiangmuChuyiFix1/font/fontello.ttf
TensorflowZhinengYidongXiangmuChuyiFix1/font/fontello.woff
TensorflowZhinengYidongXiangmuChuyiFix1/img/__init__.py
TensorflowZhinengYidongXiangmuChuyiFix1/img/annotator-glyph-sprite.png
TensorflowZhinengYidongXiangmuChuyiFix1/img/annotator-icon-sprite.png
TensorflowZhinengYidongXiangmuChuyiFix1/img/apple-touch-icon.png
TensorflowZhinengYidongXiangmuChuyiFix1/img/cancelfullscreen.png
TensorflowZhinengYidongXiangmuChuyiFix1/img/close.png
TensorflowZhinengYidongXiangmuChuyiFix1/img/fullscreen.png
TensorflowZhinengYidongXiangmuChuyiFix1/img/loader.gif
TensorflowZhinengYidongXiangmuChuyiFix1/img/menu-icon.png
TensorflowZhinengYidongXiangmuChuyiFix1/img/save.png
TensorflowZhinengYidongXiangmuChuyiFix1/img/saved.png
TensorflowZhinengYidongXiangmuChuyiFix1/img/settings-s.png
TensorflowZhinengYidongXiangmuChuyiFix1/img/settings.png
TensorflowZhinengYidongXiangmuChuyiFix1/img/star.png
TensorflowZhinengYidongXiangmuChuyiFix1/js/__init__.py
TensorflowZhinengYidongXiangmuChuyiFix1/js/epub.js
TensorflowZhinengYidongXiangmuChuyiFix1/js/epub.min.js
TensorflowZhinengYidongXiangmuChuyiFix1/js/epub.min.map
TensorflowZhinengYidongXiangmuChuyiFix1/js/hooks.min.js
TensorflowZhinengYidongXiangmuChuyiFix1/js/hooks.min.map
tensorflow_zhineng_yidong_xiangmu_chuyi_fix1-2025.3.24.0.dist-info/METADATA
tensorflow_zhineng_yidong_xiangmu_chuyi_fix1-2025.3.24.0.dist-info/WHEEL
tensorflow_zhineng_yidong_xiangmu_chuyi_fix1-2025.3.24.0.dist-info/entry_points.txt
tensorflow_zhineng_yidong_xiangmu_chuyi_fix1-2025.3.24.0.dist-info/top_level.txt
tensorflow_zhineng_yidong_xiangmu_chuyi_fix1-2025.3.24.0.dist-info/RECORD
